{
  "rankedProjects": [
    "AI in Autonomous Vehicles",
    "Blockchain for Transparent Food Supply Chains",
    "IoT for Smart Building Management",
    "Blockchain for Supply Chain Finance",
    "AI for Sentiment Analysis in Social Media",
    "Blockchain for Transparent Digital Rights Management",
    "AI for Personalized Medicine",
    "IoT-Based Environmental Monitoring Systems",
    "AI for Optimizing Transportation Networks",
    "Blockchain for Supply Chain Transparency",
    "AI for Predictive Analytics in Healthcare",
    "Blockchain for Secure Digital Contract Management",
    "AI for Real-Time Anomaly Detection",
    "AI for Real-Time Traffic Management",
    "Virtual Reality for Historical Education",
    "AI for Healthcare Diagnostics",
    "AI for Real-Time Speech Recognition",
    "Cybersecurity Measures for Smart Cities",
    "IoT for Smart Environmental Monitoring",
    "AI for Real-Time Translation"
  ],
  "scoreProjects": [
    {
      "name": "AI in Autonomous Vehicles",
      "score": 10
    },
    {
      "name": "Blockchain for Transparent Food Supply Chains",
      "score": 10
    },
    {
      "name": "IoT for Smart Building Management",
      "score": 10
    },
    {
      "name": "Blockchain for Supply Chain Finance",
      "score": 9
    },
    {
      "name": "AI for Sentiment Analysis in Social Media",
      "score": 9
    },
    {
      "name": "Blockchain for Transparent Digital Rights Management",
      "score": 8
    },
    {
      "name": "AI for Personalized Medicine",
      "score": 7
    },
    {
      "name": "IoT-Based Environmental Monitoring Systems",
      "score": 0
    },
    {
      "name": "AI for Optimizing Transportation Networks",
      "score": 0
    },
    {
      "name": "Blockchain for Supply Chain Transparency",
      "score": 0
    },
    {
      "name": "AI for Predictive Analytics in Healthcare",
      "score": 0
    },
    {
      "name": "Blockchain for Secure Digital Contract Management",
      "score": 0
    },
    {
      "name": "AI for Real-Time Anomaly Detection",
      "score": 0
    },
    {
      "name": "AI for Real-Time Traffic Management",
      "score": 0
    },
    {
      "name": "Virtual Reality for Historical Education",
      "score": 0
    },
    {
      "name": "AI for Healthcare Diagnostics",
      "score": 0
    },
    {
      "name": "AI for Real-Time Speech Recognition",
      "score": 0
    },
    {
      "name": "Cybersecurity Measures for Smart Cities",
      "score": 0
    },
    {
      "name": "IoT for Smart Environmental Monitoring",
      "score": 0
    },
    {
      "name": "AI for Real-Time Translation",
      "score": 0
    }
  ],
  "groupProjects": {
    "really-want": [
      "AI for Real-Time Speech Recognition",
      "AI for Natural Disaster Prediction",
      "AI for Real-Time Traffic Management"
    ],
    "okay-with": [
      "Cybersecurity for IoT Devices",
      "AI in Autonomous Vehicles",
      "AI for Sentiment Analysis in Social Media",
      "AI-Enhanced E-Learning Platforms"
    ],
    "dont-want": [
      "Virtual Reality for Collaborative Workspaces",
      "AI for Enhancing Customer Service",
      "Blockchain for Decentralized Data Storage",
      "AI for Enhanced Cybersecurity Threat Detection",
      "Blockchain for Transparent Supply Chain Finance",
      "AI for Automated Legal Document Analysis",
      "Machine Learning for Financial Fraud Detection",
      "IoT for Smart Home Automation",
      "AI-Powered Chatbots for Customer Service",
      "AI for Optimizing Supply Chain Logistics"
    ],
    "not-qualified": [
      "AI for Fraud Detection in E-Commerce",
      "AI for Enhanced Cyber Threat Detection",
      "Virtual Reality for Education and Training"
    ]
  },
  "checkedProjects": {
    "approved": [
      "AI for Enhancing Online Education",
      "Blockchain for Transparent Charity Operations",
      "AI for Real-Time Anomaly Detection"
    ],
    "disapproved": [
      "Blockchain for Real Estate Transactions",
      "IoT for Smart Building Management",
      "AI for Enhanced Cyber Threat Detection",
      "Blockchain for Supply Chain Finance",
      "Blockchain for Transparent Digital Rights Management",
      "AI for Financial Market Prediction",
      "IoT for Smart Home Automation",
      "IoT for Smart City Infrastructure",
      "Blockchain for Secure Healthcare Records",
      "AI for Predictive Maintenance in Transportation",
      "AI-Powered Chatbots for Customer Service",
      "Blockchain for Secure Voting Systems",
      "AI for Predictive Policing",
      "AI for Fraud Detection in Insurance Claims",
      "AI for Predictive Analytics in Sports",
      "AI for Fraud Detection in E-Commerce",
      "AI for Enhancing Customer Experience in Retail"
    ]
  },
  "rankedProjectsTime": 14.433,
  "scoreProjectsTime": 20.964,
  "groupProjectsTime": 29.513,
  "checkProjectsTime": 22.371
}